.gitignore
LICENSE
README.md
ballbeam.png
pid_agent.py
setup.cfg
setup.py
ballbeam_gym/__init__.py
ballbeam_gym/ballbeam.py
ballbeam_gym.egg-info/PKG-INFO
ballbeam_gym.egg-info/SOURCES.txt
ballbeam_gym.egg-info/dependency_links.txt
ballbeam_gym.egg-info/requires.txt
ballbeam_gym.egg-info/top_level.txt
ballbeam_gym/envs/__init__.py
ballbeam_gym/envs/balance.py
ballbeam_gym/envs/base.py
ballbeam_gym/envs/setpoint.py
ballbeam_gym/envs/throw.py