Metadata-Version: 2.1
Name: ballbeam-gym
Version: 0.0.5
Summary: Ball & beam environments for OpenAI gym
Home-page: https://github.com/simon-larsson/ballbeam-gym
Author: Simon Larsson
Author-email: simonlarsson0@gmail.com
License: MIT
Platform: UNKNOWN
Classifier: License :: OSI Approved :: MIT License
Classifier: Programming Language :: Python :: 3 :: Only
Classifier: Topic :: Scientific/Engineering
